lingdocs/__init__.py
lingdocs/cldf.py
lingdocs/cli.py
lingdocs/config.py
lingdocs/data/bibtex_schemes.json
lingdocs/data/cldf/AbbreviationTable-metadata.json
lingdocs/data/cldf/ChapterTable-metadata.json
lingdocs/data/cldf/ContributorTable-metadata.json
lingdocs/data/cldf/TopicTable-metadata.json
lingdocs/data/config.yaml
lingdocs/data/format_templates/github/basic/cookiecutter.json
lingdocs/data/format_templates/github/basic/part_template
lingdocs/data/format_templates/github/basic/{{cookiecutter.name}}/README.md
lingdocs/data/format_templates/html/basic/cookiecutter.json
lingdocs/data/format_templates/html/basic/hooks/post_gen_project.py
lingdocs/data/format_templates/html/basic/part_template
lingdocs/data/format_templates/html/basic/{{cookiecutter.name}}/index.html
lingdocs/data/format_templates/html/slides/cookiecutter.json
lingdocs/data/format_templates/html/slides/hooks/post_gen_project.py
lingdocs/data/format_templates/html/slides/{{cookiecutter.name}}/index.html
lingdocs/data/format_templates/latex/article/cookiecutter.json
lingdocs/data/format_templates/latex/article/hooks/post_gen_project.py
lingdocs/data/format_templates/latex/article/{{cookiecutter.name}}/expex-acro.sty
lingdocs/data/format_templates/latex/article/{{cookiecutter.name}}/main.tex
lingdocs/data/format_templates/latex/book/cookiecutter.json
lingdocs/data/format_templates/latex/book/hooks/post_gen_project.py
lingdocs/data/format_templates/latex/book/{{cookiecutter.name}}/expex-acro.sty
lingdocs/data/format_templates/latex/book/{{cookiecutter.name}}/main.tex
lingdocs/data/format_templates/latex/book/{{cookiecutter.name}}/titlepage.tex
lingdocs/data/format_templates/latex/handout/cookiecutter.json
lingdocs/data/format_templates/latex/handout/hooks/post_gen_project.py
lingdocs/data/format_templates/latex/handout/{{cookiecutter.name}}/main.tex
lingdocs/data/format_templates/latex/shared_preamble.tex
lingdocs/data/format_templates/mkdocs/basic/cookiecutter.json
lingdocs-0.1.4.dist-info/LICENSE
lingdocs-0.1.4.dist-info/METADATA
lingdocs-0.1.4.dist-info/WHEEL
lingdocs-0.1.4.dist-info/entry_points.txt
lingdocs-0.1.4.dist-info/RECORD
