Metadata-Version: 2.1
Name: lingdocs
Version: 0.1.4
Summary: Create data-rich linguistic documents.
Home-page: https://fl.mt/lingdocs
License: Apache-2.0
Keywords: cldf,markdown,digital linguistics
Author: Florian Matter
Author-email: flmt@mailbox.org
Requires-Python: >=3.8.1,<4.0.0
Classifier: Development Status :: 4 - Beta
Classifier: Intended Audience :: Science/Research
Classifier: License :: OSI Approved :: Apache Software License
Classifier: Natural Language :: English
Classifier: Programming Language :: Python :: 3
Classifier: Programming Language :: Python :: 3.9
Classifier: Programming Language :: Python :: 3.10
Classifier: Programming Language :: Python :: 3.11
Classifier: Programming Language :: Python :: 3.12
Classifier: Programming Language :: Python :: 3.8
Requires-Dist: cldf-rel (>=0.0.4,<0.0.5)
Requires-Dist: cldfviz (>=1.0.0,<2.0.0)
Requires-Dist: click (>=8.1.7,<9.0.0)
Requires-Dist: cookiecutter (>=2.4.0,<3.0.0)
Requires-Dist: hupper (>=1.12,<2.0)
Requires-Dist: importlib-resources (>=6.1.0,<7.0.0)
Requires-Dist: mkdocs-awesome-pages-plugin (>=2.9.2,<3.0.0)
Requires-Dist: mkdocs-enumerate-headings-plugin (>=0.6.1,<0.7.0)
Requires-Dist: mkdocs-material (>=9.4.3,<10.0.0)
Requires-Dist: mkdocs-site-urls (>=0.2.0,<0.3.0)
Requires-Dist: pandas (>=2.0.3,<3.0.0)
Requires-Dist: panflute (>=2.3.0,<3.0.0)
Requires-Dist: pycldf (>=1.35.0,<2.0.0)
Requires-Dist: python-slugify (>=8.0.1,<9.0.0)
Requires-Dist: writio (>=0.0.1,<0.0.2)
Project-URL: Bug tracker, https://www.github.com/fmatter/lingdocs/issues
Project-URL: Repository, https://www.github.com/fmatter/lingdocs
